Workbook

Sheet Master keyword list
A1: Tier | B1: Keyword | C1: Category | D1: Monthly volume (US) | E1: Competition | F1: CPC (USD) | G1: Intent | H1: Funnel stage | I1: Recommended use case | J1: Notes
A2: T1 | B2: explainable AI in finance | C2: Explainable & Auditable AI | D2: 6600 | E2: 0.18 | F2: 6.05 | G2: Commercial | H2: MOFU | I2: Landing page H1, pillar page | J2: Anchor target. Low competition, no Q2C vendor in top 10.
A3: T1 | B3: AI in finance | C3: AI for Finance (broad) | D3: 4400 | E3: 0.66 | F3: 7.88 | G3: Informational | H3: TOFU | I3: Pillar page, blog | J3: Head term. SERP dominated by editorial content.
A4: T1 | B4: finance AI | C4: AI for Finance (broad) | D4: 4400 | E4: 0.66 | F4: 7.88 | G4: Informational | H4: TOFU | I4: Pillar page, blog | J4: Synonym of above; cover same intent.
A5: T1 | B5: AI for finance | C5: AI for Finance (broad) | D5: 2400 | E5: 0.66 | F5: 7.88 | G5: Commercial | H5: MOFU | I5: Landing page H2, solution page | J5: High commercial value. Use in body, H2s.
A6: T1 | B6: AI for accounting | C6: AI for Accounting | D6: 1600 | E6: 0.68 | F6: 9.08 | G6: Commercial | H6: MOFU | I6: Solution page, blog cluster | J6: Strong secondary. Mix of educational + product SERP.
A7: T1 | B7: accounting AI | C7: AI for Accounting | D7: 3600 | E7: 0.68 | F7: 9.08 | G7: Informational | H7: TOFU | I7: Pillar page, blog | J7: Head term for accounting cluster.
A8: T1 | B8: AI in accounting | C8: AI for Accounting | D8: 2400 | E8: 0.68 | F8: 9.08 | G8: Informational | H8: TOFU | I8: Pillar page, blog | J8: Same intent as 'accounting AI'.
A9: T1 | B9: AI in financial services | C9: AI for Finance (broad) | D9: 1300 | E9: 0.48 | F9: 9.29 | G9: Commercial | H9: MOFU | I9: Solution page, blog | J9: Banking-leaning intent. Address in FAQ + related content.
A10: T1 | B10: AI agents in finance | C10: AI Agents in Finance | D10: 590 | E10: 0.41 | F10: 11.47 | G10: Commercial | H10: BOFU | I10: Landing page H1, solution page | J10: Direct match to product. Moderate competition.
A11: T1 | B11: AI agents for finance | C11: AI Agents in Finance | D11: 210 | E11: 0.41 | F11: 12.01 | G11: Commercial | H11: BOFU | I11: Landing page H1, ad copy | J11: Exact phrase the assignment uses. Must be on page.
A12: T1 | B12: AI invoice automation | C12: AI Invoice & AP Automation | D12: 390 | E12: 0.25 | F12: 22.71 | G12: Commercial | H12: BOFU | I12: Capability page, ad copy | J12: Low competition + very high CPC. Strong quick win.
A13: T1 | B13: AI billing | C13: AI Billing & Subscription | D13: 210 | E13: 0.14 | F13: 14.25 | G13: Commercial | H13: BOFU | I13: Capability page, ad copy | J13: Very low competition. Outranks BillingPlatform at scale.
... A101: T3 | B101: AI for revenue recognition | C101: Revenue Recognition / ASC 606 | D101: 10 | E101: 0 | F101: 0 | G101: Commercial | H101: BOFU | I101: Body copy, positioning | J101: Sub-10 volume but exact match to Zuora product.

Sheet Summary by category
A1: Category summary
A2: Counts and volumes computed live from the Master keyword list sheet.
A4: Category | B4: Keyword count | C4: Total monthly volume | D4: Average competition | E4: Recommended primary use case
A5: AI Agents in Finance | B5: =COUNTIF('Master keyword list'!C2:C101,A5) -> 5 | C5: =SUMIF('Master keyword list'!C2:C101,A5,'Master keyword list'!D2:D101) -> 1100 | D5: =AVERAGEIF('Master keyword list'!C2:C101,A5,'Master keyword list'!E2:E101) -> 0.49 | E5: Landing page H1 + ad copy
A6: AI Audit & Governance | B6: =COUNTIF('Master keyword list'!C2:C101,A6) -> 10 | C6: =SUMIF('Master keyword list'!C2:C101,A6,'Master keyword list'!D2:D101) -> 3980 | D6: =AVERAGEIF('Master keyword list'!C2:C101,A6,'Master keyword list'!E2:E101) -> 0.474 | E6: Trust/compliance hub + FAQ schema
A7: AI Billing & Subscription | B7: =COUNTIF('Master keyword list'!C2:C101,A7) -> 5 | C7: =SUMIF('Master keyword list'!C2:C101,A7,'Master keyword list'!D2:D101) -> 1310 | D7: =AVERAGEIF('Master keyword list'!C2:C101,A7,'Master keyword list'!E2:E101) -> 0.43 | E7: Capability pages + product comparison content
A8: AI Invoice & AP Automation | B8: =COUNTIF('Master keyword list'!C2:C101,A8) -> 17 | C8: =SUMIF('Master keyword list'!C2:C101,A8,'Master keyword list'!D2:D101) -> 22380 | D8: =AVERAGEIF('Master keyword list'!C2:C101,A8,'Master keyword list'!E2:E101) -> 0.28647059 | E8: Capability sub-pages + paid ads (highest CPC)
A9: AI for Accounting | B9: =COUNTIF('Master keyword list'!C2:C101,A9) -> 9 | C9: =SUMIF('Master keyword list'!C2:C101,A9,'Master keyword list'!D2:D101) -> 13440 | D9: =AVERAGEIF('Master keyword list'!C2:C101,A9,'Master keyword list'!E2:E101) -> 0.51555556 | E9: Solution page + comparison blog series
A10: AI for CFO / Finance Leaders | B10: =COUNTIF('Master keyword list'!C2:C101,A10) -> 5 | C10: =SUMIF('Master keyword list'!C2:C101,A10,'Master keyword list'!D2:D101) -> 590 | D10: =AVERAGEIF('Master keyword list'!C2:C101,A10,'Master keyword list'!E2:E101) -> 0.644 | E10: Persona-led landing pages + email campaigns
A11: AI for Finance (broad) | B11: =COUNTIF('Master keyword list'!C2:C101,A11) -> 12 | C11: =SUMIF('Master keyword list'!C2:C101,A11,'Master keyword list'!D2:D101) -> 17280 | D11: =AVERAGEIF('Master keyword list'!C2:C101,A11,'Master keyword list'!E2:E101) -> 0.57333333 | E11: Pillar page + thought-leadership blog cluster
A12: Agentic AI for Finance | B12: =COUNTIF('Master keyword list'!C2:C101,A12) -> 5 | C12: =SUMIF('Master keyword list'!C2:C101,A12,'Master keyword list'!D2:D101) -> 630 | D12: =AVERAGEIF('Master keyword list'!C2:C101,A12,'Master keyword list'!E2:E101) -> 0.588 | E12: Landing page + first-mover blog content
A13: Explainable & Auditable AI | B13: =COUNTIF('Master keyword list'!C2:C101,A13) -> 6 | C13: =SUMIF('Master keyword list'!C2:C101,A13,'Master keyword list'!D2:D101) -> 18180 | D13: =AVERAGEIF('Master keyword list'!C2:C101,A13,'Master keyword list'!E2:E101) -> 0.096666667 | E13: Anchor landing page (Tier 1 SEO target) + glossary
A14: Finance Automation (general) | B14: =COUNTIF('Master keyword list'!C2:C101,A14) -> 8 | C14: =SUMIF('Master keyword list'!C2:C101,A14,'Master keyword list'!D2:D101) -> 2900 | D14: =AVERAGEIF('Master keyword list'!C2:C101,A14,'Master keyword list'!E2:E101) -> 0.23 | E14: Solution pages + adjacent blog content
A15: Question / PAA | B15: =COUNTIF('Master keyword list'!C2:C101,A15) -> 16 | C15: =SUMIF('Master keyword list'!C2:C101,A15,'Master keyword list'!D2:D101) -> 39620 | D15: =AVERAGEIF('Master keyword list'!C2:C101,A15,'Master keyword list'!E2:E101) -> 0.403125 | E15: FAQ schema (FAQPage) + glossary entries
A16: Revenue Recognition / ASC 606 | B16: =COUNTIF('Master keyword list'!C2:C101,A16) -> 2 | C16: =SUMIF('Master keyword list'!C2:C101,A16,'Master keyword list'!D2:D101) -> 20 | D16: =AVERAGEIF('Master keyword list'!C2:C101,A16,'Master keyword list'!E2:E101) -> 0.495 | E16: Body copy + product positioning
A17: Total | B17: =SUM(B5:B16) -> 100 | C17: =SUM(C5:C16) -> 121430 | D17: =AVERAGE('Master keyword list'!E2:E101) -> 0.4175
A19: Tier breakdown
A20: Tier | B20: Definition | C20: Keyword count | D20: Total monthly volume | E20: Average competition
A21: T1 | B21: Anchor targets — primary keywords the website, ads, and email campaigns lead with. | C21: =COUNTIF('Master keyword list'!A2:A101,A21) -> 21 | D21: =SUMIF('Master keyword list'!A2:A101,A21,'Master keyword list'!D2:D101) -> 74180 | E21: =AVERAGEIF('Master keyword list'!A2:A101,A21,'Master keyword list'!E2:E101) -> 0.51952381
A22: T2 | B22: Supporting — secondary keywords for H2/H3 sections, blog cluster, comparison content. | C22: =COUNTIF('Master keyword list'!A2:A101,A22) -> 32 | D22: =SUMIF('Master keyword list'!A2:A101,A22,'Master keyword list'!D2:D101) -> 34960 | E22: =AVERAGEIF('Master keyword list'!A2:A101,A22,'Master keyword list'!E2:E101) -> 0.4275
A23: T3 | B23: Long-tail and strategic — niche use cases, FAQ schema, body copy, positioning terms. | C23: =COUNTIF('Master keyword list'!A2:A101,A23) -> 47 | D23: =SUMIF('Master keyword list'!A2:A101,A23,'Master keyword list'!D2:D101) -> 12290 | E23: =AVERAGEIF('Master keyword list'!A2:A101,A23,'Master keyword list'!E2:E101) -> 0.36510638
A25: Methodology
A26: Data pulled from SEMrush MCP, US database, May 2026. 100 keywords selected from a candidate pool of ~250 via phrase_related, phrase_questions, phrase_fullsearch, and phrase_these reports across 12 seed terms (AI for finance, AI billing, AI accounting, AI revenue recognition, agentic AI finance, AI invoice processing, AI for CFO, explainable AI, AI audit, finance automation, AI agents, and adjacent terms). Filtered for relevance to Zuora AI agents for quote-to-cash. Volume and competition values are SEMrush US monthly searches. CPC is in USD.
